r2cloud
